{".class": "MypyFile", "_fullname": "GoogleMapImageLib", "_name": null, "is_stub": false, "names": {".class": "SymbolTable", "__doc__": {".class": "SymbolTableNode", "kind": "Gdef", "node": {".class": "Var", "flags": ["is_ready"], "fullname": "GoogleMapImageLib.__doc__", "name": "__doc__", "type": "builtins.str"}}, "__file__": {".class": "SymbolTableNode", "kind": "Gdef", "node": {".class": "Var", "flags": ["is_ready"], "fullname": "GoogleMapImageLib.__file__", "name": "__file__", "type": "builtins.str"}}, "__name__": {".class": "SymbolTableNode", "kind": "Gdef", "node": {".class": "Var", "flags": ["is_ready"], "fullname": "GoogleMapImageLib.__name__", "name": "__name__", "type": "builtins.str"}}, "__package__": {".class": "SymbolTableNode", "kind": "Gdef", "node": {".class": "Var", "flags": ["is_ready"], "fullname": "GoogleMapImageLib.__package__", "name": "__package__", "type": "builtins.str"}}, "download_map_image": {".class": "SymbolTableNode", "kind": "Gdef", "node": {".class": "FuncDef", "arg_kinds": [0, 0, 0, 0, 1, 1, 1], "arg_names": ["latitude", "longitude", "key", "fileName", "width", "height", "zoom"], "flags": [], "fullname": "GoogleMapImageLib.download_map_image", "name": "download_map_image", "type": null}}, "download_satelite_image": {".class": "SymbolTableNode", "kind": "Gdef", "node": {".class": "FuncDef", "arg_kinds": [0, 0, 0, 0, 1, 1, 1], "arg_names": ["latitude", "longitude", "key", "fileName", "width", "height", "zoom"], "flags": [], "fullname": "GoogleMapImageLib.download_satelite_image", "name": "download_satelite_image", "type": null}}, "get_pic_width_meters": {".class": "SymbolTableNode", "kind": "Gdef", "node": {".class": "FuncDef", "arg_kinds": [0, 0, 0], "arg_names": ["latitude", "pic_width_pixels", "zoom"], "flags": [], "fullname": "GoogleMapImageLib.get_pic_width_meters", "name": "get_pic_width_meters", "type": null}}, "get_second_point": {".class": "SymbolTableNode", "kind": "Gdef", "node": {".class": "FuncDef", "arg_kinds": [0, 0, 0, 0], "arg_names": ["lat1", "long1", "distance", "direction"], "flags": [], "fullname": "GoogleMapImageLib.get_second_point", "name": "get_second_point", "type": null}}, "get_second_point_moving_EW": {".class": "SymbolTableNode", "kind": "Gdef", "node": {".class": "FuncDef", "arg_kinds": [0, 0, 0, 1], "arg_names": ["lat1", "long1", "distance", "west"], "flags": [], "fullname": "GoogleMapImageLib.get_second_point_moving_EW", "name": "get_second_point_moving_EW", "type": null}}, "get_second_point_moving_NS": {".class": "SymbolTableNode", "kind": "Gdef", "node": {".class": "FuncDef", "arg_kinds": [0, 0, 0, 1], "arg_names": ["lat1", "long1", "distance", "south"], "flags": [], "fullname": "GoogleMapImageLib.get_second_point_moving_NS", "name": "get_second_point_moving_NS", "type": null}}, "is_within_city": {".class": "SymbolTableNode", "kind": "Gdef", "node": {".class": "FuncDef", "arg_kinds": [0, 0, 0, 0], "arg_names": ["latitude", "longitude", "city_name", "key"], "flags": [], "fullname": "GoogleMapImageLib.is_within_city", "name": "is_within_city", "type": null}}, "math": {".class": "SymbolTableNode", "cross_ref": "math", "kind": "ModuleRef"}, "requests": {".class": "SymbolTableNode", "cross_ref": "requests", "kind": "ModuleRef"}, "urllib": {".class": "SymbolTableNode", "cross_ref": "urllib", "kind": "ModuleRef"}, "urllib.request": {".class": "SymbolTableNode", "kind": "UnboundImported"}}, "path": "/Users/azchen/Documents/Projects/cs6316/ImageToCrime/GoogleMapImageLib.py"}
